{
  "type": "create:sequenced_assembly",
  "ingredient": {
    "tag": "forge:nuggets/iron"
  },
  "loops": 1,
  "results": [
    {
      "count": 6,
      "item": "cgs:nail"
    }
  ],
  "sequence": [
    {
      "type": "create:cutting",
      "ingredients": [
        {
          "item": "minecraft:iron_nugget"
        }
      ],
      "results": [
        {
          "item": "minecraft:iron_nugget"
        }
      ]
    },
    {
      "type": "create:pressing",
      "ingredients": [
        {
          "item": "minecraft:iron_nugget"
        }
      ],
      "results": [
        {
          "item": "minecraft:iron_nugget"
        }
      ]
    }
  ],
  "transitionalItem": {
    "item": "minecraft:iron_nugget"
  }
}